qq_tr
