Metadata-Version: 2.1
Name: qq-tr-free
Version: 0.0.2
Summary: qq translate for free
Home-page: http://github.com/ffreemt/qq-tr-free
Author: mikeee
License: MIT License
Download-URL: https://github.com/ffreemt/qq-tr-free/archive/v_0.0.2.tar.gz
Keywords: machine translation,free,scraping
Platform: UNKNOWN
Classifier: Development Status :: 3 - Alpha
Classifier: Intended Audience :: Developers
Classifier: Programming Language :: Python :: 3
Classifier: Programming Language :: Python :: 3.6
Classifier: License :: OSI Approved :: MIT License
